Workbook

Sheet Dashboard
A1: Khalsni System Build Plan - Production Checklist
A2: Generated: 2026-05-04
A4: Area | B4: Total Tasks | C4: Not Started | D4: In Progress | E4: Blocked | F4: Done | G4: High Priority | H4: Critical Priority
A5: Backend Build | B5: =COUNTA('Backend Build'!$A$2:$A$500) -> 16 | C5: =COUNTIF('Backend Build'!$H$2:$H$500,"Not Started") -> 0 | D5: =COUNTIF('Backend Build'!$H$2:$H$500,"In Progress") -> 0 | E5: =COUNTIF('Backend Build'!$H$2:$H$500,"Blocked") -> 0 | F5: =COUNTIF('Backend Build'!$H$2:$H$500,"Done") -> 16 | G5: =COUNTIF('Backend Build'!$G$2:$G$500,"High") -> 3 | H5: =COUNTIF('Backend Build'!$G$2:$G$500,"Critical") -> 12
A6: UI Screens | B6: =COUNTA('UI Screens'!$A$2:$A$500) -> 14 | C6: =COUNTIF('UI Screens'!$G$2:$G$500,"Not Started") -> 14 | D6: =COUNTIF('UI Screens'!$G$2:$G$500,"In Progress") -> 0 | E6: =COUNTIF('UI Screens'!$G$2:$G$500,"Blocked") -> 0 | F6: =COUNTIF('UI Screens'!$G$2:$G$500,"Done") -> 0 | G6: =COUNTIF('UI Screens'!$F$2:$F$500,"High") -> 5 | H6: =COUNTIF('UI Screens'!$F$2:$F$500,"Critical") -> 6
A7: Workflow Logic | B7: =COUNTA('Workflow Logic'!$A$2:$A$500) -> 10 | C7: =COUNTIF('Workflow Logic'!$H$2:$H$500,"Not Started") -> 10 | D7: =COUNTIF('Workflow Logic'!$H$2:$H$500,"In Progress") -> 0 | E7: =COUNTIF('Workflow Logic'!$H$2:$H$500,"Blocked") -> 0 | F7: =COUNTIF('Workflow Logic'!$H$2:$H$500,"Done") -> 0 | G7: =COUNTIF('Workflow Logic'!$G$2:$G$500,"High") -> 3 | H7: =COUNTIF('Workflow Logic'!$G$2:$G$500,"Critical") -> 7
A8: Security Checklist | B8: =COUNTA('Security Checklist'!$A$2:$A$500) -> 11 | C8: =COUNTIF('Security Checklist'!$H$2:$H$500,"Not Started") -> 11 | D8: =COUNTIF('Security Checklist'!$H$2:$H$500,"In Progress") -> 0 | E8: =COUNTIF('Security Checklist'!$H$2:$H$500,"Blocked") -> 0 | F8: =COUNTIF('Security Checklist'!$H$2:$H$500,"Done") -> 0 | G8: =COUNTIF('Security Checklist'!$G$2:$G$500,"High") -> 1 | H8: =COUNTIF('Security Checklist'!$G$2:$G$500,"Critical") -> 9
A9: Testing QA | B9: =COUNTA('Testing QA'!$A$2:$A$500) -> 12 | C9: =COUNTIF('Testing QA'!$H$2:$H$500,"Not Started") -> 12 | D9: =COUNTIF('Testing QA'!$H$2:$H$500,"In Progress") -> 0 | E9: =COUNTIF('Testing QA'!$H$2:$H$500,"Blocked") -> 0 | F9: =COUNTIF('Testing QA'!$H$2:$H$500,"Done") -> 0 | G9: =COUNTIF('Testing QA'!$G$2:$G$500,"High") -> 5 | H9: =COUNTIF('Testing QA'!$G$2:$G$500,"Critical") -> 6
A10: Deployment | B10: =COUNTA(Deployment!$A$2:$A$500) -> 10 | C10: =COUNTIF(Deployment!$H$2:$H$500,"Not Started") -> 10 | D10: =COUNTIF(Deployment!$H$2:$H$500,"In Progress") -> 0 | E10: =COUNTIF(Deployment!$H$2:$H$500,"Blocked") -> 0 | F10: =COUNTIF(Deployment!$H$2:$H$500,"Done") -> 0 | G10: =COUNTIF(Deployment!$G$2:$G$500,"High") -> 2 | H10: =COUNTIF(Deployment!$G$2:$G$500,"Critical") -> 7
A11: Missing Decisions | B11: =COUNTA('Missing Decisions'!$A$2:$A$500) -> 10 | C11: =COUNTIF('Missing Decisions'!$H$2:$H$500,"Not Started") -> 10 | D11: =COUNTIF('Missing Decisions'!$H$2:$H$500,"In Progress") -> 0 | E11: =COUNTIF('Missing Decisions'!$H$2:$H$500,"Blocked") -> 0 | F11: =COUNTIF('Missing Decisions'!$H$2:$H$500,"Done") -> 0 | G11: =COUNTIF('Missing Decisions'!$G$2:$G$500,"High") -> 5 | H11: =COUNTIF('Missing Decisions'!$G$2:$G$500,"Critical") -> 2
A13: Recommended Build Order
A14: 1 | B14: Freeze models and migrations
A15: 2 | B15: Seed roles, permissions, service categories, and demo data
A16: 3 | B16: Implement selectors and permission helpers
A17: 4 | B17: Implement workflow transition service and audit logs
A18: 5 | B18: Implement document upload/verification security
A19: 6 | B19: Implement notifications and reports
A20: 7 | B20: Build UI screens using permission checks
A21: 8 | B21: Write tests for roles, object access, workflow, and files
A22: 9 | B22: Deploy staging with PostgreSQL, media storage, logs, backups
A23: 10 | B23: User acceptance testing before production launch

Sheet Master Roadmap
A1: ID | B1: Phase | C1: Task | D1: Details | E1: App/Module | F1: Output/Artifact | G1: Priority | H1: Status | I1: Dependency | J1: Acceptance Criteria
A2: BE-001 | B2: Foundation | C2: Create Django app structure | D2: Create apps: core, accounts, services, orders, documents, workflow, notifications, reports. Keep business logic out of views. | E2: Project | F2: Apps created and added to INSTALLED_APPS | G2: Critical | H2: Done | J2: Project imports without errors
A3: BE-002 | B3: Foundation | C3: Create core choices/constants | D3: Define UserRole, OrderStatus, DocumentType, NotificationType, PaymentStatus, Priority constants using TextChoices. | E3: core | F3: core/choices.py | G3: Critical | H3: Done | I3: BE-001 | J3: No hardcoded status strings in models/services/views
A4: BE-003 | B4: Models | C4: Finalize service models | D4: ServiceCategory, Service, ServiceRequiredDocument, ServicePricingRule if needed. Include active flags and ordering. | E4: services | F4: services/models.py | G4: Critical | H4: Done | I4: BE-002 | J4: Admin can create service, define required docs, and deactivate service safely
A5: BE-004 | B5: Models | C5: Finalize order models | D5: Order, OrderAssignment, OrderNote, OrderStatusHistory or audit log fields. Include client, service, status, assigned employee/provider, dates, pricing fields. | E5: orders | F5: orders/models.py | G5: Critical | H5: Done | I5: BE-002, BE-003 | J5: Order lifecycle supports all workflow statuses
A6: BE-005 | B6: Models | C6: Finalize document models | D6: Secure file model with original filename, safe stored filename, MIME, size, document type, verification status, final document flag. | E6: documents | F6: documents/models.py | G6: Critical | H6: Done | I6: BE-004 | J6: Documents are linked to order and user, with verification state
A7: BE-006 | B7: Models | C7: Create audit log model | D7: Log actor, action, old_status, new_status, metadata, IP/user agent optional, timestamp. | E7: orders/reports | F7: OrderAuditLog model | G7: Critical | H7: Done | I7: BE-004 | J7: Every important order action creates audit log
A8: BE-007 | B8: Models | C8: Create notification model | D8: Recipient, title, message, related order, type, read flag, channel, timestamp. | E8: notifications | F8: Notification model | G8: High | H8: Done | I8: BE-004 | J8: Users can receive and read system notifications
A9: BE-008 | B9: Migrations | C9: Run and review migrations | D9: Generate migrations after model finalization; inspect SQL if needed before applying. | E9: All apps | F9: Migration files | G9: Critical | H9: Done | I9: BE-003 to BE-007 | J9: Migrations apply cleanly on empty DB
A10: BE-009 | B10: Permissions | C10: Create role setup command | D10: Create groups: client, employee, provider, admin. Assign permissions from production permission matrix. | E10: accounts | F10: setup_roles command | G10: Critical | H10: Done | I10: BE-008 | J10: Running command seeds all groups and permissions
A11: BE-010 | B11: Permissions | C11: Create permission helpers | D11: Reusable functions: is_admin, is_employee, is_provider, is_client, can_view_order, can_edit_order, can_download_document. | E11: orders/documents | F11: permissions.py | G11: Critical | H11: Done | I11: BE-009 | J11: No duplicated role logic in views/templates
A12: BE-011 | B12: Data Access | C12: Create selectors | D12: get_orders_for_user, get_documents_for_user, get_notifications_for_user. Enforce object-level access. | E12: orders/documents | F12: selectors.py | G12: Critical | H12: Done | I12: BE-010 | J12: Users never see unauthorized records
A13: BE-012 | B13: Services | C13: Create order service layer | D13: Functions for submit_order, review_order, request_missing_info, assign_provider, start_work, complete_provider_work, verify_order, deliver_order, cancel_order. | E13: orders | F13: services.py | G13: Critical | H13: Done | I13: BE-011 | J13: All status-changing actions go through service layer
A14: BE-013 | B14: Services | C14: Create document service layer | D14: Validate file type/size, upload required docs, verify/reject docs, upload final docs, secure download. | E14: documents | F14: services.py | G14: Critical | H14: Done | I14: BE-005, BE-010 | J14: Unsafe file uploads rejected; access checked before download
... A74: DEP-010 | B74: Release | C74: Production launch checklist | D74: Migrations, roles seed, admin user, service seed, backups, monitoring, smoke tests. | E74: Ops | F74: release checklist | G74: Critical | H74: Not Started | I74: QA-012, DEP-009 | J74: Production smoke test passes
A75: DEC-001 | B75: Business Rule | C75: Who can assign provider? | D75: Decide if employee can assign any provider or only admin can assign providers. | E75: orders | F75: policy decision | G75: High | H75: Not Started | J75: Documented rule and implemented permission
A76: DEC-002 | B76: Business Rule | C76: Can employee see all orders? | D76: Decide if employees see all submitted orders or only orders assigned to them. | E76: orders | F76: policy decision | G76: Critical | H76: Not Started | J76: Selector logic matches decision
A77: DEC-003 | B77: Business Rule | C77: Payment handling | D77: Decide if payment is external/manual report only or integrated payment gateway. | E77: payments/reports | F77: payment scope | G77: High | H77: Not Started | J77: Payment status model or report flow finalized
A78: DEC-004 | B78: Business Rule | C78: Cancellation/refund rules | D78: Define when clients can cancel and whether payment/refund status changes. | E78: orders/payments | F78: policy decision | G78: High | H78: Not Started | J78: Cancellation rules implemented and tested
A79: DEC-005 | B79: Documents | C79: Allowed file types and max size | D79: Define accepted types: PDF/JPG/PNG/docx? Max MB per file. | E79: documents | F79: file policy | G79: Critical | H79: Not Started | J79: Upload validation constants finalized
A80: DEC-006 | B80: Documents | C80: Document retention policy | D80: Define how long to keep uploaded files and audit logs. | E80: documents/legal | F80: retention policy | G80: Medium | H80: Not Started | J80: Retention policy documented
A81: DEC-007 | B81: Notifications | C81: Notification channels | D81: Choose MVP channels: internal only, email, SMS, WhatsApp later. | E81: notifications | F81: channel decision | G81: Medium | H81: Not Started | J81: Notification service supports selected channels
A82: DEC-008 | B82: Reports | C82: Required reports | D82: Define reports needed by admin: order volume, status aging, provider performance, revenue/payment report. | E82: reports | F82: report list | G82: High | H82: Not Started | J82: Reports dashboard scope finalized
A83: DEC-009 | B83: Localization | C83: Arabic/English support | D83: Decide whether MVP needs bilingual UI and data fields for all services/messages. | E83: templates/models | F83: language decision | G83: Medium | H83: Not Started | J83: UI/message localization plan selected
A84: DEC-010 | B84: Deployment | C84: Hosting target | D84: Decide VPS/Coolify, domain/subdomain, backup location, email provider. | E84: Ops | F84: deployment decision | G84: High | H84: Not Started | J84: Staging deployment plan finalized

Sheet Backend Build
A1: ID | B1: Phase | C1: Task | D1: Details | E1: App/Module | F1: Output/Artifact | G1: Priority | H1: Status | I1: Dependency | J1: Acceptance Criteria
A2: BE-001 | B2: Foundation | C2: Create Django app structure | D2: Create apps: core, accounts, services, orders, documents, workflow, notifications, reports. Keep business logic out of views. | E2: Project | F2: Apps created and added to INSTALLED_APPS | G2: Critical | H2: Done | J2: Project imports without errors
A3: BE-002 | B3: Foundation | C3: Create core choices/constants | D3: Define UserRole, OrderStatus, DocumentType, NotificationType, PaymentStatus, Priority constants using TextChoices. | E3: core | F3: core/choices.py | G3: Critical | H3: Done | I3: BE-001 | J3: No hardcoded status strings in models/services/views
A4: BE-003 | B4: Models | C4: Finalize service models | D4: ServiceCategory, Service, ServiceRequiredDocument, ServicePricingRule if needed. Include active flags and ordering. | E4: services | F4: services/models.py | G4: Critical | H4: Done | I4: BE-002 | J4: Admin can create service, define required docs, and deactivate service safely
A5: BE-004 | B5: Models | C5: Finalize order models | D5: Order, OrderAssignment, OrderNote, OrderStatusHistory or audit log fields. Include client, service, status, assigned employee/provider, dates, pricing fields. | E5: orders | F5: orders/models.py | G5: Critical | H5: Done | I5: BE-002, BE-003 | J5: Order lifecycle supports all workflow statuses
A6: BE-005 | B6: Models | C6: Finalize document models | D6: Secure file model with original filename, safe stored filename, MIME, size, document type, verification status, final document flag. | E6: documents | F6: documents/models.py | G6: Critical | H6: Done | I6: BE-004 | J6: Documents are linked to order and user, with verification state
A7: BE-006 | B7: Models | C7: Create audit log model | D7: Log actor, action, old_status, new_status, metadata, IP/user agent optional, timestamp. | E7: orders/reports | F7: OrderAuditLog model | G7: Critical | H7: Done | I7: BE-004 | J7: Every important order action creates audit log
A8: BE-007 | B8: Models | C8: Create notification model | D8: Recipient, title, message, related order, type, read flag, channel, timestamp. | E8: notifications | F8: Notification model | G8: High | H8: Done | I8: BE-004 | J8: Users can receive and read system notifications
A9: BE-008 | B9: Migrations | C9: Run and review migrations | D9: Generate migrations after model finalization; inspect SQL if needed before applying. | E9: All apps | F9: Migration files | G9: Critical | H9: Done | I9: BE-003 to BE-007 | J9: Migrations apply cleanly on empty DB
A10: BE-009 | B10: Permissions | C10: Create role setup command | D10: Create groups: client, employee, provider, admin. Assign permissions from production permission matrix. | E10: accounts | F10: setup_roles command | G10: Critical | H10: Done | I10: BE-008 | J10: Running command seeds all groups and permissions
A11: BE-010 | B11: Permissions | C11: Create permission helpers | D11: Reusable functions: is_admin, is_employee, is_provider, is_client, can_view_order, can_edit_order, can_download_document. | E11: orders/documents | F11: permissions.py | G11: Critical | H11: Done | I11: BE-009 | J11: No duplicated role logic in views/templates
A12: BE-011 | B12: Data Access | C12: Create selectors | D12: get_orders_for_user, get_documents_for_user, get_notifications_for_user. Enforce object-level access. | E12: orders/documents | F12: selectors.py | G12: Critical | H12: Done | I12: BE-010 | J12: Users never see unauthorized records
A13: BE-012 | B13: Services | C13: Create order service layer | D13: Functions for submit_order, review_order, request_missing_info, assign_provider, start_work, complete_provider_work, verify_order, deliver_order, cancel_order. | E13: orders | F13: services.py | G13: Critical | H13: Done | I13: BE-011 | J13: All status-changing actions go through service layer
A14: BE-013 | B14: Services | C14: Create document service layer | D14: Validate file type/size, upload required docs, verify/reject docs, upload final docs, secure download. | E14: documents | F14: services.py | G14: Critical | H14: Done | I14: BE-005, BE-010 | J14: Unsafe file uploads rejected; access checked before download
... A17: BE-016 | B17: Seed Data | C17: Create demo data command | D17: Seed service categories, services, required documents, demo users for each role. | E17: core/services | F17: seed_demo command | G17: Medium | H17: Done | I17: BE-009 | J17: System can be tested end-to-end quickly

Sheet UI Screens
A1: ID | B1: Phase | C1: Task | D1: Details | E1: App/Module | F1: Priority | G1: Status | H1: Dependency | I1: Acceptance Criteria
A2: UI-001 | B2: Layout | C2: Create base layout | D2: Navbar/sidebar changes based on user role. Include notification icon and profile menu. | E2: templates/core | F2: Critical | G2: Not Started | H2: BE-009 | I2: Only allowed navigation items appear
A3: UI-002 | B3: Client | C3: Client dashboard | D3: Show active orders, missing document requests, completed orders, recent notifications. | E3: orders/templates | F3: High | G3: Not Started | H3: BE-011 | I3: Client only sees own data
A4: UI-003 | B4: Client | C4: Create order screen | D4: Service selection, dynamic required documents, notes, submit as draft/submitted. | E4: orders/templates | F4: Critical | G4: Not Started | H4: BE-003, BE-012 | I4: Client can create valid order
A5: UI-004 | B5: Client | C5: My orders screen | D5: List own orders with status, date, service, next required action. | E5: orders/templates | F5: High | G5: Not Started | H5: BE-011 | I5: No other users' orders shown
A6: UI-005 | B6: Client | C6: Missing documents response screen | D6: Upload requested documents and resubmit order. | E6: documents/templates | F6: Critical | G6: Not Started | H6: BE-013 | I6: Upload only allowed while order is missing_info
A7: UI-006 | B7: Employee | C7: Employee review queue | D7: Show submitted/resubmitted orders needing review. | E7: orders/templates | F7: Critical | G7: Not Started | H7: BE-011, BE-012 | I7: Employee can review allowed orders
A8: UI-007 | B8: Employee | C8: Order review detail | D8: Actions: request missing docs, reject, assign provider, add note, verify documents. | E8: orders/templates | F8: Critical | G8: Not Started | H8: BE-012, BE-013 | I8: Every button maps to protected backend action
A9: UI-008 | B9: Provider | C9: Provider assigned orders | D9: Show provider's assigned orders only. | E9: orders/templates | F9: High | G9: Not Started | H9: BE-011 | I9: Provider sees assigned orders only
A10: UI-009 | B10: Provider | C10: Provider work detail | D10: Actions: start work, update work note, upload final document, mark completed. | E10: orders/documents templates | F10: Critical | G10: Not Started | H10: BE-012, BE-013 | I10: Provider can update only assigned active orders
A11: UI-010 | B11: Admin | C11: Admin reports dashboard | D11: High-level counts, orders by status, service volume, provider performance, missing documents. | E11: reports/templates | F11: High | G11: Not Started | H11: BE-006, BE-011 | I11: Admin sees full reporting
A12: UI-011 | B12: Admin | C12: Manage services/prices screens | D12: CRUD service categories, services, required documents, pricing. | E12: services/templates | F12: High | G12: Not Started | H12: BE-003 | I12: Only admin can modify services/prices
... A15: UI-014 | B15: Shared | C15: Notification center | D15: List notifications, mark read, link to related order where allowed. | E15: notifications/templates | F15: Medium | G15: Not Started | H15: BE-014 | I15: Unauthorized order links are blocked

Sheet Workflow Logic
A1: ID | B1: Phase | C1: Task | D1: Details | E1: App/Module | F1: Output/Artifact | G1: Priority | H1: Status | I1: Dependency | J1: Acceptance Criteria
A2: WF-001 | B2: Status Engine | C2: Define allowed transitions | D2: Central transition map: draft→submitted, submitted→under_review, under_review→missing_info/assigned/rejected, etc. | E2: workflow | F2: rules.py | G2: Critical | H2: Not Started | I2: BE-002 | J2: No invalid transition can be saved
A3: WF-002 | B3: Status Engine | C3: Create transition validator | D3: validate_order_transition(current, next) with clear ValidationError. | E3: workflow | F3: services.py | G3: Critical | H3: Not Started | I3: WF-001 | J3: Invalid transitions raise error
A4: WF-003 | B4: Role Rules | C4: Map transition permissions | D4: Define which role can perform each transition; object ownership still checked. | E4: workflow/orders | F4: transition_permissions.py | G4: Critical | H4: Not Started | I4: WF-001, BE-010 | J4: Only authorized role can transition status
A5: WF-004 | B5: Atomic Updates | C5: Wrap workflow actions in transactions | D5: Use transaction.atomic for status updates, assignments, audit log, notification creation. | E5: orders/workflow | F5: service functions | G5: Critical | H5: Not Started | I5: BE-012 | J5: No partial update when error occurs
A6: WF-005 | B6: Missing Info Flow | C6: Implement missing document request | D6: Employee selects missing document type and note; client notification created; status becomes missing_info. | E6: orders/documents | F6: request_missing_info service | G6: Critical | H6: Not Started | I6: WF-004, BE-014 | J6: Client sees required missing documents
A7: WF-006 | B7: Assignment Flow | C7: Implement provider assignment | D7: Employee/admin assigns provider; provider notification created; order status assigned. | E7: orders | F7: assign_provider service | G7: Critical | H7: Not Started | I7: WF-004 | J7: Assigned provider can see order
A8: WF-007 | B8: Provider Flow | C8: Implement provider completion | D8: Provider starts work, uploads final document, marks completed_by_provider. | E8: orders/documents | F8: provider services | G8: High | H8: Not Started | I8: WF-006, BE-013 | J8: Final document linked and visible to employee/admin
A9: WF-008 | B9: Verification Flow | C9: Implement final verification | D9: Employee/admin reviews final document and sets verified/delivered or returns to missing_info/rework. | E9: orders/documents | F9: verify service | G9: High | H9: Not Started | I9: WF-007 | J9: Client notified when delivered
A10: WF-009 | B10: Cancellation Rules | C10: Define cancellation rules | D10: Client may cancel only draft/submitted; employee limited; admin can cancel most non-delivered orders. | E10: workflow | F10: cancellation service | G10: High | H10: Not Started | I10: WF-003 | J10: Cancellation follows business policy
A11: WF-010 | B11: Audit Trail | C11: Log every transition | D11: Every transition stores old/new status, actor, action, note, timestamp. | E11: orders | F11: audit service | G11: Critical | H11: Not Started | I11: BE-006, WF-004 | J11: Audit log complete for all status changes

Sheet Security Checklist
A1: ID | B1: Phase | C1: Task | D1: Details | E1: App/Module | F1: Output/Artifact | G1: Priority | H1: Status | I1: Dependency | J1: Acceptance Criteria
A2: SEC-001 | B2: Auth | C2: Require login everywhere | D2: Protect all dashboard, order, document, notification, and report views with LoginRequiredMixin/decorators. | E2: All views | F2: login protection | G2: Critical | H2: Not Started | I2: BE-009 | J2: Anonymous users cannot access private screens
A3: SEC-002 | B3: Authorization | C3: Server-side permission checks | D3: Use PermissionRequiredMixin or explicit checks before every protected action. | E3: All views/services | F3: backend authorization | G3: Critical | H3: Not Started | I3: BE-010 | J3: Direct URL/API calls cannot bypass UI
A4: SEC-003 | B4: Object Access | C4: Object-level filtering | D4: Never use Order.objects.all() in user-facing views. Use selectors. | E4: orders/documents | F4: selectors enforced | G4: Critical | H4: Not Started | I4: BE-011 | J4: Users can access only permitted objects
A5: SEC-004 | B5: Files | C5: Secure uploads | D5: Validate extension, MIME, size; use generated safe filenames; block executable files. | E5: documents | F5: file validation | G5: Critical | H5: Not Started | I5: BE-013 | J5: Malicious/oversized files rejected
A6: SEC-005 | B6: Files | C6: Secure downloads | D6: Download endpoint checks can_view_document/can_download_document before serving file. | E6: documents | F6: download view | G6: Critical | H6: Not Started | I6: BE-013 | J6: Unauthorized file download returns 403/404
A7: SEC-006 | B7: CSRF | C7: Enable CSRF protection | D7: Use Django CSRF middleware and tokens in all forms. | E7: Project/templates | F7: CSRF enabled | G7: Critical | H7: Not Started | I7: UI forms | J7: POST without token rejected
A8: SEC-007 | B8: Forms | C8: Use ModelForms with validation | D8: Do not trust hidden fields for client/provider/price/status; set sensitive fields in backend. | E8: All forms | F8: forms.py | G8: Critical | H8: Not Started | I8: BE-012 | J8: User cannot tamper with status/ownership
A9: SEC-008 | B9: Admin | C9: Restrict admin actions | D9: Only staff/admin can access Django admin; readonly fields for audit fields. | E9: admin | F9: admin.py | G9: High | H9: Not Started | I9: BE-015 | J9: Non-admin roles blocked from admin
A10: SEC-009 | B10: Settings | C10: Production security settings | D10: Configure ALLOWED_HOSTS, CSRF_TRUSTED_ORIGINS, DEBUG=False, secure cookies, HSTS after HTTPS. | E10: settings | F10: production settings | G10: Critical | H10: Not Started | I10: Deployment | J10: Security checks pass
A11: SEC-010 | B11: Logging | C11: Security logging | D11: Log failed permission attempts and important actions without leaking sensitive data. | E11: core | F11: logging config | G11: Medium | H11: Not Started | I11: SEC-002 | J11: Suspicious actions visible in logs
A12: SEC-011 | B12: OWASP | C12: Broken access control review | D12: Manually test role bypass attempts: direct URLs, changing IDs, hidden button actions. | E12: QA | F12: security test checklist | G12: Critical | H12: Not Started | I12: SEC-001 to SEC-005 | J12: No broken access control found

Sheet Testing QA
A1: ID | B1: Phase | C1: Task | D1: Details | E1: App/Module | F1: Output/Artifact | G1: Priority | H1: Status | I1: Dependency | J1: Acceptance Criteria
A2: QA-001 | B2: Unit Tests | C2: Test role helpers | D2: Test is_admin/is_employee/is_provider/is_client and permission helper behavior. | E2: accounts/orders | F2: test_permissions.py | G2: Critical | H2: Not Started | I2: BE-010 | J2: Role helper tests pass
A3: QA-002 | B3: Unit Tests | C3: Test selectors | D3: Each role sees only expected orders/documents/notifications. | E3: orders/documents | F3: test_selectors.py | G3: Critical | H3: Not Started | I3: BE-011 | J3: No unauthorized records returned
A4: QA-003 | B4: Unit Tests | C4: Test workflow transitions | D4: Allowed transitions pass; invalid transitions fail. | E4: workflow | F4: test_workflow.py | G4: Critical | H4: Not Started | I4: WF-001, WF-002 | J4: Transition tests pass
A5: QA-004 | B5: Integration Tests | C5: Test client order flow | D5: Client creates order, uploads docs, submits, sees own timeline. | E5: orders/documents | F5: client flow test | G5: High | H5: Not Started | I5: UI-003 | J5: End-to-end client flow passes
A6: QA-005 | B6: Integration Tests | C6: Test employee review flow | D6: Employee reviews, requests missing info, assigns provider, verifies final output. | E6: orders | F6: employee flow test | G6: High | H6: Not Started | I6: UI-006, UI-007 | J6: Employee flow passes
A7: QA-006 | B7: Integration Tests | C7: Test provider flow | D7: Provider sees assigned order, starts work, uploads final document, completes. | E7: orders/documents | F7: provider flow test | G7: High | H7: Not Started | I7: UI-008, UI-009 | J7: Provider flow passes
A8: QA-007 | B8: Security Tests | C8: Test direct URL bypass | D8: Try opening another client's order/document using ID manipulation. | E8: All views | F8: access control test | G8: Critical | H8: Not Started | I8: SEC-003, SEC-005 | J8: Unauthorized access blocked
A9: QA-008 | B9: Security Tests | C9: Test file upload attacks | D9: Try invalid extensions, large files, wrong MIME, dangerous names. | E9: documents | F9: file upload test | G9: Critical | H9: Not Started | I9: SEC-004 | J9: Bad files rejected
A10: QA-009 | B10: UI Tests | C10: Manual role UI review | D10: Login as each role and verify visible screens/buttons match permission matrix. | E10: templates | F10: manual QA checklist | G10: High | H10: Not Started | I10: UI-001 to UI-014 | J10: UI matches backend permissions
A11: QA-010 | B11: Data Tests | C11: Audit log completeness | D11: Check each action creates correct audit log record. | E11: orders | F11: audit tests | G11: High | H11: Not Started | I11: WF-010 | J11: Audit log present for all important actions
A12: QA-011 | B12: Performance | C12: Basic query performance review | D12: Use select_related/prefetch_related on order lists and detail pages. | E12: orders | F12: query optimization | G12: Medium | H12: Not Started | I12: UI lists | J12: No excessive duplicate queries
A13: QA-012 | B13: UAT | C13: User acceptance testing | D13: Test real business scenarios with admin/employee/provider/client accounts. | E13: Project | F13: UAT signoff | G13: Critical | H13: Not Started | I13: All core features | J13: Client confirms flow is correct

Sheet Deployment
A1: ID | B1: Phase | C1: Task | D1: Details | E1: App/Module | F1: Output/Artifact | G1: Priority | H1: Status | I1: Dependency | J1: Acceptance Criteria
A2: DEP-001 | B2: Environment | C2: Create .env structure | D2: SECRET_KEY, DEBUG, DATABASE_URL, ALLOWED_HOSTS, CSRF_TRUSTED_ORIGINS, EMAIL settings, media path. | E2: Project | F2: .env.example | G2: Critical | H2: Not Started | I2: BE complete | J2: Settings loaded from environment
A3: DEP-002 | B3: Database | C3: Use PostgreSQL | D3: Configure PostgreSQL for staging/production; avoid SQLite in production. | E3: settings/db | F3: database config | G3: Critical | H3: Not Started | I3: DEP-001 | J3: Migrations run on PostgreSQL
A4: DEP-003 | B4: Static Files | C4: Configure static files | D4: Use collectstatic and WhiteNoise or reverse proxy static serving. | E4: Project | F4: static config | G4: High | H4: Not Started | I4: DEP-001 | J4: Static assets load in production
A5: DEP-004 | B5: Media Files | C5: Configure media storage | D5: Local protected media for MVP or S3-compatible storage later; document backup path. | E5: documents | F5: media config | G5: Critical | H5: Not Started | I5: SEC-005 | J5: Uploaded files persist and are protected
A6: DEP-005 | B6: Email | C6: Configure email backend | D6: SMTP settings for notifications/password reset. Database notifications remain primary. | E6: notifications | F6: email config | G6: Medium | H6: Not Started | I6: BE-014 | J6: Test email sends successfully
A7: DEP-006 | B7: Backups | C7: Create backup plan | D7: Database daily backups + media backup + restore test. | E7: Ops | F7: backup procedure | G7: Critical | H7: Not Started | I7: DEP-002, DEP-004 | J7: Restore test succeeds
A8: DEP-007 | B8: Logging | C8: Configure production logging | D8: App logs, error logs, access logs; avoid sensitive data in logs. | E8: Project | F8: logging config | G8: High | H8: Not Started | I8: SEC-010 | J8: Errors traceable in production
A9: DEP-008 | B9: Staging | C9: Deploy staging environment | D9: Use Coolify/Docker or VPS setup with domain, HTTPS, env vars, DB, media. | E9: Ops | F9: staging deployment | G9: Critical | H9: Not Started | I9: DEP-001 to DEP-007 | J9: Staging accessible over HTTPS
A10: DEP-009 | B10: Security | C10: Run Django deployment checks | D10: Run python manage.py check --deploy and fix warnings. | E10: Project | F10: deployment check report | G10: Critical | H10: Not Started | I10: DEP-008 | J10: No critical deployment warnings
A11: DEP-010 | B11: Release | C11: Production launch checklist | D11: Migrations, roles seed, admin user, service seed, backups, monitoring, smoke tests. | E11: Ops | F11: release checklist | G11: Critical | H11: Not Started | I11: QA-012, DEP-009 | J11: Production smoke test passes

Sheet Missing Decisions
A1: ID | B1: Phase | C1: Task | D1: Details | E1: App/Module | F1: Output/Artifact | G1: Priority | H1: Status | I1: Dependency | J1: Acceptance Criteria
A2: DEC-001 | B2: Business Rule | C2: Who can assign provider? | D2: Decide if employee can assign any provider or only admin can assign providers. | E2: orders | F2: policy decision | G2: High | H2: Not Started | J2: Documented rule and implemented permission
A3: DEC-002 | B3: Business Rule | C3: Can employee see all orders? | D3: Decide if employees see all submitted orders or only orders assigned to them. | E3: orders | F3: policy decision | G3: Critical | H3: Not Started | J3: Selector logic matches decision
A4: DEC-003 | B4: Business Rule | C4: Payment handling | D4: Decide if payment is external/manual report only or integrated payment gateway. | E4: payments/reports | F4: payment scope | G4: High | H4: Not Started | J4: Payment status model or report flow finalized
A5: DEC-004 | B5: Business Rule | C5: Cancellation/refund rules | D5: Define when clients can cancel and whether payment/refund status changes. | E5: orders/payments | F5: policy decision | G5: High | H5: Not Started | J5: Cancellation rules implemented and tested
A6: DEC-005 | B6: Documents | C6: Allowed file types and max size | D6: Define accepted types: PDF/JPG/PNG/docx? Max MB per file. | E6: documents | F6: file policy | G6: Critical | H6: Not Started | J6: Upload validation constants finalized
A7: DEC-006 | B7: Documents | C7: Document retention policy | D7: Define how long to keep uploaded files and audit logs. | E7: documents/legal | F7: retention policy | G7: Medium | H7: Not Started | J7: Retention policy documented
A8: DEC-007 | B8: Notifications | C8: Notification channels | D8: Choose MVP channels: internal only, email, SMS, WhatsApp later. | E8: notifications | F8: channel decision | G8: Medium | H8: Not Started | J8: Notification service supports selected channels
A9: DEC-008 | B9: Reports | C9: Required reports | D9: Define reports needed by admin: order volume, status aging, provider performance, revenue/payment report. | E9: reports | F9: report list | G9: High | H9: Not Started | J9: Reports dashboard scope finalized
A10: DEC-009 | B10: Localization | C10: Arabic/English support | D10: Decide whether MVP needs bilingual UI and data fields for all services/messages. | E10: templates/models | F10: language decision | G10: Medium | H10: Not Started | J10: UI/message localization plan selected
A11: DEC-010 | B11: Deployment | C11: Hosting target | D11: Decide VPS/Coolify, domain/subdomain, backup location, email provider. | E11: Ops | F11: deployment decision | G11: High | H11: Not Started | J11: Staging deployment plan finalized
